app/__init__.py
app/cg_celery.py
app/choices.py
app/permissions.json
app/routes.py
app/run_server.py
app/server.py
app/service.py
app/settings.py
app/utils.py
app/validator.py
app/validator_new.py
app/__pycache__/_choices.cpython-39.pyc
app/__pycache__/cg_celery.cpython-310.pyc
app/__pycache__/cg_celery.cpython-39.pyc
app/__pycache__/choices.cpython-310.pyc
app/__pycache__/choices.cpython-39.pyc
app/__pycache__/routes.cpython-310.pyc
app/__pycache__/routes.cpython-39.pyc
app/__pycache__/run_server.cpython-310.pyc
app/__pycache__/server.cpython-310.pyc
app/__pycache__/server.cpython-39.pyc
app/__pycache__/service.cpython-310.pyc
app/__pycache__/service.cpython-39.pyc
app/__pycache__/settings.cpython-310.pyc
app/__pycache__/settings.cpython-39.pyc
app/__pycache__/utils.cpython-310.pyc
app/__pycache__/utils.cpython-39.pyc
app/__pycache__/validator.cpython-310.pyc
app/__pycache__/validator.cpython-39.pyc
app/__pycache__/validator_new.cpython-310.pyc
app/__pycache__/validator_new.cpython-39.pyc
app/services/user_service.py
app/services/__pycache__/user_service.cpython-310.pyc
app/tasks/callback.py
app/tasks/delegator.py
app/tasks/execution.py
app/tasks/helpers.py
app/tasks/notice_preview.py
app/tasks/report.py
app/tasks/tasks.py
app/tasks/__pycache__/callback.cpython-310.pyc
app/tasks/__pycache__/callback.cpython-39.pyc
app/tasks/__pycache__/delegator.cpython-310.pyc
app/tasks/__pycache__/delegator.cpython-39.pyc
app/tasks/__pycache__/execution.cpython-310.pyc
app/tasks/__pycache__/execution.cpython-39.pyc
app/tasks/__pycache__/helpers.cpython-310.pyc
app/tasks/__pycache__/helpers.cpython-39.pyc
app/tasks/__pycache__/invoice_automation.cpython-39.pyc
app/tasks/__pycache__/notice_preview.cpython-310.pyc
app/tasks/__pycache__/notice_preview.cpython-39.pyc
app/tasks/__pycache__/physical_notice.cpython-39.pyc
app/tasks/__pycache__/report.cpython-310.pyc
app/tasks/__pycache__/report.cpython-39.pyc
app/tasks/__pycache__/reports.cpython-39.pyc
my_quart_app-2.0.0.dist-info/METADATA
my_quart_app-2.0.0.dist-info/WHEEL
my_quart_app-2.0.0.dist-info/entry_points.txt
my_quart_app-2.0.0.dist-info/top_level.txt
my_quart_app-2.0.0.dist-info/RECORD
