Metadata-Version: 2.1
Name: my_quart_app
Version: 2.0.0
Requires-Dist: aiofiles ==0.8.0
Requires-Dist: aioredis ==1.3.1
Requires-Dist: amqp ==2.6.1
Requires-Dist: asyncpg ==0.26.0
Requires-Dist: billiard ==3.6.4.0
Requires-Dist: black ==20.8b1
Requires-Dist: blinker ==1.4
Requires-Dist: boto3 ==1.21.29
Requires-Dist: botocore ==1.24.30
Requires-Dist: celery ==4.4.7
Requires-Dist: certifi ==2021.10.8
Requires-Dist: chardet ==3.0.4
Requires-Dist: click-didyoumean ==0.0.3
Requires-Dist: click-plugins ==1.1.1
Requires-Dist: click-repl ==0.2.0
Requires-Dist: flower ==0.9.5
Requires-Dist: h2 ==4.0.0
Requires-Dist: hiredis ==2.0.0
Requires-Dist: hpack ==4.0.0
Requires-Dist: httpcore ==0.12.0
Requires-Dist: httpx ==0.16.1
Requires-Dist: humanize ==3.0.1
Requires-Dist: Hypercorn ==0.11.2
Requires-Dist: hyperframe ==6.0.0
Requires-Dist: idna ==2.10
Requires-Dist: itsdangerous ==1.1.0
Requires-Dist: Jinja2 ==2.11.2
Requires-Dist: jmespath ==0.10.0
Requires-Dist: kombu ==4.6.11
Requires-Dist: MarkupSafe ==1.1.1
Requires-Dist: multidict ==5.0.0
Requires-Dist: priority ==1.3.0
Requires-Dist: prometheus-client ==0.8.0
Requires-Dist: prompt-toolkit ==3.0.8
Requires-Dist: python-dateutil ==2.8.1
Requires-Dist: python-dotenv ==0.20.0
Requires-Dist: pytoml ==0.1.21
Requires-Dist: pytz ==2021.3
Requires-Dist: Quart ==0.17.0
Requires-Dist: quart-schema ==0.11.1
Requires-Dist: redis ==3.5.3
Requires-Dist: requests ==2.25.1
Requires-Dist: rfc3986 ==1.4.0
Requires-Dist: s3transfer ==0.5.0
Requires-Dist: shortuuid ==1.0.1
Requires-Dist: six ==1.15.0
Requires-Dist: sniffio ==1.2.0
Requires-Dist: sortedcontainers ==2.2.2
Requires-Dist: toml ==0.10.2
Requires-Dist: typing-extensions ==3.7.4.3
Requires-Dist: urllib3 ==1.26.9
Requires-Dist: uvicorn ==0.20.0
Requires-Dist: vine ==1.3.0
Requires-Dist: wcwidth ==0.2.5
Requires-Dist: Werkzeug ==2.1.2
Requires-Dist: wsproto ==0.15.0
Requires-Dist: zipp ==3.3.1
Requires-Dist: marshmallow ==3.12.1
Requires-Dist: XlsxWriter ==3.0.2
Requires-Dist: nest-asyncio ==1.5.1
Requires-Dist: pandas ==1.4.1
Requires-Dist: phonenumbers ==8.12.45
